HISTORY.rst
LICENSE
MANIFEST.in
README.md
requirements.txt
setup.cfg
setup.py
STRISH/__init__.py
STRISH/readwrite.py
STRISH/test_readwrite.py
STRISH/utils.py
STRISH.egg-info/PKG-INFO
STRISH.egg-info/SOURCES.txt
STRISH.egg-info/dependency_links.txt
STRISH.egg-info/not-zip-safe
STRISH.egg-info/requires.txt
STRISH.egg-info/top_level.txt
STRISH/core/STRISH_Obj.py
STRISH/core/__init__.py
STRISH/plotting/__init__.py
STRISH/plotting/qc.py
STRISH/plotting/spatial.py
STRISH/plotting/windows.py
STRISH/preprocessing/__init__.py
STRISH/preprocessing/preprocessing.py
STRISH/preprocessing/test_preprocessing.py
STRISH/test/__init__.py
STRISH/test/test_stat.py
STRISH/tools/__init__.py
STRISH/tools/registration.py
STRISH/tools/stat.py