Metadata-Version: 1.2
Name: STRISH
Version: 0.2.1
Summary: Spatial TRanscriptomic In Situ Hybridization (STRISH)
Home-page: https://github.com/BiomedicalMachineLearning/STRISH
Author: Genomics and Machine Learning lab
Author-email: uqmtra12@uq.edu.au
License: BSD license
Keywords: STRISH
Platform: UNKNOWN
Classifier: Development Status :: 2 - Pre-Alpha
Classifier: Intended Audience :: Developers
Classifier: License :: OSI Approved :: BSD License
Classifier: Natural Language :: English
Classifier: Programming Language :: Python :: 3
Classifier: Programming Language :: Python :: 3.5
Classifier: Programming Language :: Python :: 3.6
Classifier: Programming Language :: Python :: 3.7
Classifier: Programming Language :: Python :: 3.8
Requires-Python: >=3.5
